tchoupy/__init__.py
tchoupy/conversionsystem_metaclass.py
tchoupy/future_updates.txt
tchoupy/qty.py
tchoupy/requirements.txt
tchoupy/databases/HEP_database.py
tchoupy/databases/__init__.py
tchoupy/systems/CGS_mod.py
tchoupy/systems/Cosmo_mod.py
tchoupy/systems/HEP_mod.py
tchoupy/systems/Imperial_mod.py
tchoupy/systems/SI_mod.py
tchoupy/systems/__init__.py
tchoupy-1.0.2.dist-info/LICENSE
tchoupy-1.0.2.dist-info/METADATA
tchoupy-1.0.2.dist-info/WHEEL
tchoupy-1.0.2.dist-info/top_level.txt
tchoupy-1.0.2.dist-info/RECORD
