Metadata-Version: 2.1
Name: tchoupy
Version: 1.0.2
Summary: Time-saving tool for unit conversions and dimensional quantity computations
Author-email: Martin Teuscher <teuscher.edu@gmail.com>
License: MIT License
Project-URL: Homepage, https://github.com/Martinuche/tchoupy
Keywords: units,unit conversion,conversion systems,physics,dimensional quantities
Classifier: License :: OSI Approved :: MIT License
Classifier: Programming Language :: Python :: 3
Classifier: Intended Audience :: Science/Research
Classifier: Operating System :: OS Independent
Classifier: Topic :: Scientific/Engineering
Classifier: Topic :: Scientific/Engineering :: Physics
Requires-Python: >=3.8
License-File: LICENSE
Requires-Dist: numpy>=1.21.5
Requires-Dist: regex>=2.5.135
Requires-Dist: scipy>=1.10.1
